django_lsp/__init__.py
django_lsp/server.py
django_lsp-0.1.0.dev0.dist-info/METADATA
django_lsp-0.1.0.dev0.dist-info/WHEEL
django_lsp-0.1.0.dev0.dist-info/entry_points.txt
django_lsp-0.1.0.dev0.dist-info/licenses/LICENSE
django_lsp-0.1.0.dev0.dist-info/RECORD
