Metadata-Version: 2.1
Name: django-lsp
Version: 0.1.0.dev0
Summary: Django Language Server Protocol
Author-email: Josh Thomas <josh@joshthomas.dev>
License: MIT License
License-File: LICENSE
Classifier: Development Status :: 1 - Planning
Classifier: Framework :: Django
Classifier: Framework :: Django :: 3.2
Classifier: Framework :: Django :: 4.2
Classifier: Framework :: Django :: 5.0
Classifier: License :: OSI Approved :: MIT License
Classifier: Operating System :: OS Independent
Classifier: Programming Language :: Python
Classifier: Programming Language :: Python :: 3
Classifier: Programming Language :: Python :: 3 :: Only
Classifier: Programming Language :: Python :: 3.8
Classifier: Programming Language :: Python :: 3.9
Classifier: Programming Language :: Python :: 3.10
Classifier: Programming Language :: Python :: 3.11
Classifier: Programming Language :: Python :: 3.12
Classifier: Programming Language :: Python :: Implementation :: CPython
Requires-Python: >=3.8
Requires-Dist: pygls>=1.3.0
